[
	{
		"items": [
			{
				"lat": 56.763289168545775,
				"lon": 19.710329692033458,
				"begin_angle": 191.0,
				"curve": 0.0,
				"duration": 1800.0,
				"length": 6.0,
				"port_dev": 0.0,
				"starboard_dev": 0.0
			}
		],
		"start_time": 1594800097
	},
	{
		"items": [
			{
				"lat": 56.775542101928146,
				"lon": 19.87948780290307,
				"begin_angle": 201.0,
				"curve": 0.0,
				"duration": 900.0,
				"length": 3.75,
				"port_dev": 0.0,
				"starboard_dev": 0.0
			},
			{
				"lat": 56.717325450639485,
				"lon": 19.838958807975263,
				"begin_angle": 237.0,
				"curve": 0.0,
				"duration": 600.0,
				"length": 2.5,
				"port_dev": 0.0,
				"starboard_dev": 0.0
			},
			{
				"lat": 56.694690364752844,
				"lon": 19.775481323459527,
				"begin_angle": 178.0,
				"curve": 0.0,
				"duration": 300.0,
				"length": 1.25,
				"port_dev": 0.0,
				"starboard_dev": 0.0
			},
			{
				"lat": 56.67390084338614,
				"lon": 19.776689752292057,
				"begin_angle": 156.0,
				"curve": 0.0,
				"duration": 1200.0,
				"length": 5.0,
				"port_dev": 0.0,
				"starboard_dev": 0.0
			}
		],
		"start_time": 1594800097
	},
	{
		"items": [
			{
				"lat": 56.78772391642137,
				"lon": 19.998252500093496,
				"begin_angle": 203.0,
				"curve": 0.0,
				"duration": 1200.0,
				"length": 5.0,
				"port_dev": 0.0,
				"starboard_dev": 0.0
			},
			{
				"lat": 56.711205345875676,
				"lon": 19.939283317974404,
				"begin_angle": 203.0,
				"curve": 0.0,
				"duration": 900.0,
				"length": 0.0,
				"port_dev": 0.0,
				"starboard_dev": 0.0
			},
			{
				"lat": 56.711205345875676,
				"lon": 19.939283317974404,
				"begin_angle": 203.0,
				"curve": 0.0,
				"duration": 600.0,
				"length": 2.5,
				"port_dev": 0.0,
				"starboard_dev": 0.0
			}
		],
		"start_time": 1594800097
	},
	{
		"items": [
			{
				"lat": 56.602125410361516,
				"lon": 19.953737482050904,
				"begin_angle": 290.0,
				"curve": 0.0,
				"duration": 1200.0,
				"length": 4.0,
				"port_dev": 0.0,
				"starboard_dev": 0.0
			},
			{
				"lat": 56.62485928913518,
				"lon": 19.840292455307782,
				"begin_angle": 270.0,
				"curve": 0.0,
				"duration": 900.0,
				"length": 3.0,
				"port_dev": 0.0,
				"starboard_dev": 0.0
			},
			{
				"lat": 56.624826376916936,
				"lon": 19.749777897684435,
				"begin_angle": 300.0,
				"curve": 0.0,
				"duration": 300.0,
				"length": 1.0,
				"port_dev": 0.0,
				"starboard_dev": 0.0
			}
		],
		"start_time": 1594800097
	}
]