[
	{
		"id": "target0",
		"cat": 0,
		"lat": 60.07754537249147,
		"lon": 30.085941941899403,
		"SOG": 12.0,
		"COG": 191.0,
		"first_detect_dist": 5.0,
		"cross_dist": 0,
		"timestamp": 1594800097
	},
	{
		"id": "target1",
		"cat": 0,
		"lat": 60.08976139300475,
		"lon": 30.27178861050338,
		"SOG": 15.0,
		"COG": 201.0,
		"first_detect_dist": 5.0,
		"cross_dist": 0,
		"timestamp": 1594800097
	},
	{
		"id": "target2",
		"cat": 0,
		"lat": 60.10189646939333,
		"lon": 30.40228538288636,
		"SOG": 15.0,
		"COG": 203.0,
		"first_detect_dist": 5.0,
		"cross_dist": 0,
		"timestamp": 1594800097
	},
	{
		"id": "target3",
		"cat": 0,
		"lat": 59.916411673032314,
		"lon": 30.353137377036465,
		"SOG": 12.0,
		"COG": 290.0,
		"first_detect_dist": 5.0,
		"cross_dist": 0,
		"timestamp": 1594800097
	}
]