[{"solution_type":0,"path":{"items":[{"lat":60.0,"lon":30.0,"begin_angle":0.0,"curve":0.0,"duration":300.0,"length":1.25,"port_dev":0.0,"starboard_dev":0.0},{"lat":60.02077864465808,"lon":30.0,"begin_angle":0.0,"curve":0.0,"duration":14091.995746612549,"length":58.71664894421895,"port_dev":0.0,"starboard_dev":0.0}],"start_time":1594730579},"msg":"","solver_name":"Main"},{"solution_type":0,"path":{"items":[{"lat":60.0,"lon":30.0,"begin_angle":0.0,"curve":0.0,"duration":198.0,"length":0.825,"port_dev":0.0,"starboard_dev":0.0},{"lat":60.01371391286226,"lon":30.0,"begin_angle":0.0,"curve":0.0,"duration":198.0,"length":0.825,"port_dev":0.0,"starboard_dev":0.0},{"lat":60.02742779704328,"lon":30.0,"begin_angle":0.0,"curve":0.0,"duration":13521.126760563371,"length":56.33802816901406,"port_dev":0.0,"starboard_dev":0.0},{"lat":60.96386123368089,"lon":30.0,"begin_angle":0.0,"curve":0.0,"duration":482.8732394366307,"length":2.0119718309859566,"port_dev":0.0,"starboard_dev":0.0},{"lat":60.99730117264798,"lon":30.0,"begin_angle":0.0,"curve":0.0,"duration":1.0,"length":0.0,"port_dev":0.0,"starboard_dev":0.0}],"start_time":1594730579},"msg":"by custom solver #0 with criterion value of 6.713977","solver_name":"RVO"}]